functions_by_sercantopcu/README.md
functions_by_sercantopcu/math_functions.py
functions_by_sercantopcu-0.3.0.dist-info/WHEEL
functions_by_sercantopcu-0.3.0.dist-info/METADATA
functions_by_sercantopcu-0.3.0.dist-info/RECORD
